protobug/__init__.py
protobug/__main__.py
protobug/_core.py
protobug/_reader.py
protobug/_version.py
protobug/_writer.py
protobug/py.typed
protobug-0.3.0.dist-info/METADATA
protobug-0.3.0.dist-info/WHEEL
protobug-0.3.0.dist-info/licenses/LICENSE
protobug-0.3.0.dist-info/RECORD
