Metadata-Version: 2.4
Name: protobug
Version: 0.3.0
Summary: A pythonic protobuf library using dataclasses and enums
Project-URL: Documentation, https://github.com/yt-dlp/protobug?tab=readme-ov-file
Project-URL: Repository, https://github.com/yt-dlp/protobug
Project-URL: Issues, https://github.com/yt-dlp/protobug/issues
Project-URL: Source, https://github.com/yt-dlp/protobug
Author-email: Simon Sawicki <contact@grub4k.dev>
License: This is free and unencumbered software released into the public domain.
License-File: LICENSE
Keywords: protobuf
Classifier: Development Status :: 5 - Production/Stable
Classifier: Programming Language :: Python
Classifier: Programming Language :: Python :: 3.9
Classifier: Programming Language :: Python :: 3.10
Classifier: Programming Language :: Python :: 3.11
Classifier: Programming Language :: Python :: 3.12
Classifier: Programming Language :: Python :: 3.13
Classifier: Programming Language :: Python :: Implementation :: CPython
Requires-Python: >=3.9
